jenovum/__init__.py
jenovum-0.1.0.dist-info/METADATA
jenovum-0.1.0.dist-info/WHEEL
jenovum-0.1.0.dist-info/licenses/LICENSE
jenovum-0.1.0.dist-info/RECORD
