Metadata-Version: 2.4
Name: jenovum
Version: 0.1.0
Summary: Agentic framework for building intelligent applications.
Author-email: Roman Manasipov <romantheorphys@gmail.com>
License-Expression: MIT
License-File: LICENSE
Requires-Python: >=3.10
